alu_register.v
module alu_register #(parameter WIDTH = 8) (
    input wire                  clk_i,
    input wire                  rst_i,
    input wire [WIDTH-1:0]      first_i,
    input wire [WIDTH-1:0]      second_i,
    input wire [2:0]            opcode_i,
    output reg [WIDTH-1:0]      result_o
);
    reg [WIDTH-1:0] result_reg;

    always @(posedge clk_i) begin
        if (rst_i)
            result_reg <= 0;
        else begin
            case (opcode_i)
                3'b000: result_reg <= ~(first_i & second_i);
                3'b001: result_reg <= first_i ^ second_i;
                3'b010: result_reg <= first_i + second_i;
                3'b011: result_reg <= $signed(first_i) >>> second_i;
                3'b100: result_reg <= first_i | second_i;
                3'b101: result_reg <= first_i << second_i;
                3'b110: result_reg <=  ~first_i;
                3'b111: result_reg <= (first_i < second_i) ? 1 : 0;

                default: result_reg <= 0;
            endcase
        end
    end

    always @(posedge clk_i) begin
        result_o <= result_reg;
    end

endmodule

alu_register_tb.v
`timescale 1ns / 1ps

module alu_register_tb;
    parameter WIDTH = 8;

    reg clk;
    reg rst;
    reg [WIDTH-1:0] first;
    reg [WIDTH-1:0] second;
    reg [2:0] opcode;
    wire [WIDTH-1:0] result;

    // Instantiate the unit under test
    alu_register #(.WIDTH(WIDTH)) uut (
        .clk_i(clk),
        .rst_i(rst),
        .first_i(first),
        .second_i(second),
        .opcode_i(opcode),
        .result_o(result)
    );

    // Clock generation
    initial begin
        clk = 0;
        forever #5 clk = ~clk;
    end

    initial begin
        $dumpfile("wave.vcd");
        $dumpvars;
    end

    // Test procedure
    initial begin
        // Initialize inputs
        rst = 1;
        first = 0;
        second = 0;
        opcode = 0;

        // Reset the module
        #10;
        rst = 0;

        // Test NAND operation
        opcode = 3'b000;
        first = 8'b10101010;
        second = 8'b11001100;

        #20;  // Wait 2 cycles. Why?
              /*
                "Результат операции, исполняемой в текущий такт, сохранен
                 в регистре на следующий такт"
              */

        if (result !== ~(8'b10101010 & 8'b11001100)) $display("NAND test failed");

        // Test XOR operation
        opcode = 3'b001;
        first = 8'b11110000;
        second = 8'b10101010;
        #20;
        if (result !== (8'b11110000 ^ 8'b10101010)) $display("XOR test failed");

        // Test ADD operation
        opcode = 3'b010;
        first = 8'd100;
        second = 8'd50;
        #20;
        if (result !== 8'd150) $display("ADD test failed");

        // Test ASR operation (arithmetic shift right)
        opcode = 3'b011;
        first = 8'b10011001; // -103 in 2's complement
        second = 2;
        #20;
        if (result !== 8'b11100110) $display("ASR test failed"); // -26 after shift

        // Test OR operation
        opcode = 3'b100;
        first = 8'b00110011;
        second = 8'b01010101;
        #20;
        if (result !== (8'b00110011 | 8'b01010101)) $display("OR test failed");

        // Test LSL operation (logical shift left)
        opcode = 3'b101;
        first = 8'b00001111;
        second = 2;
        #20;
        if (result !== 8'b00111100) $display("LSL test failed");

        // Test NOT operation
        opcode = 3'b110;
        first = 8'b01010101;
        #20;
        if (result !== 8'b10101010) $display("NOT test failed");

        // Test LT operation (less than)
        opcode = 3'b111;
        first = 8'd50;
        second = 8'd100;
        #20;
        if (result !== 8'b00000001) $display("LT test 1 failed");

        first = 8'd100;
        second = 8'd50;
        #20;
        if (result !== 8'b00000000) $display("LT test 2 failed");

        // Test reset
        rst = 1;
        #20;
        if (result !== 0) $display("Reset test failed");

        $display("All tests completed");
        $finish;
    end

endmodule

wave.vcd
$date
	Mon Mar 24 14:26:37 2025
$end
$version
	Icarus Verilog
$end
$timescale
	1ps
$end
$scope module alu_register_tb $end
$var wire 8 ! result [7:0] $end
$var parameter 32 " WIDTH $end
$var reg 1 # clk $end
$var reg 8 $ first [7:0] $end
$var reg 3 % opcode [2:0] $end
$var reg 1 & rst $end
$var reg 8 ' second [7:0] $end
$scope module uut $end
$var wire 1 # clk_i $end
$var wire 8 ( first_i [7:0] $end
$var wire 3 ) opcode_i [2:0] $end
$var wire 1 & rst_i $end
$var wire 8 * second_i [7:0] $end
$var parameter 32 + WIDTH $end
$var reg 8 , result_o [7:0] $end
$var reg 8 - result_reg [7:0] $end
$upscope $end
$upscope $end
$enddefinitions $end
$comment Show the parameter values. $end
$dumpall
b1000 +
b1000 "
$end
#0
$dumpvars
bx -
bx ,
b0 *
b0 )
b0 (
b0 '
1&
b0 %
b0 $
0#
bx !
$end
#5000
b0 -
1#
#10000
0#
b11001100 '
b11001100 *
b10101010 $
b10101010 (
0&
#15000
b0 !
b0 ,
b1110111 -
1#
#20000
0#
#25000
b1110111 !
b1110111 ,
1#
#30000
0#
b10101010 '
b10101010 *
b11110000 $
b11110000 (
b1 %
b1 )
#35000
b1011010 -
1#
#40000
0#
#45000
b1011010 !
b1011010 ,
1#
#50000
0#
b110010 '
b110010 *
b1100100 $
b1100100 (
b10 %
b10 )
#55000
b10010110 -
1#
#60000
0#
#65000
b10010110 !
b10010110 ,
1#
#70000
0#
b10 '
b10 *
b10011001 $
b10011001 (
b11 %
b11 )
#75000
b11100110 -
1#
#80000
0#
#85000
b11100110 !
b11100110 ,
1#
#90000
0#
b1010101 '
b1010101 *
b110011 $
b110011 (
b100 %
b100 )
#95000
b1110111 -
1#
#100000
0#
#105000
b1110111 !
b1110111 ,
1#
#110000
0#
b10 '
b10 *
b1111 $
b1111 (
b101 %
b101 )
#115000
b111100 -
1#
#120000
0#
#125000
b111100 !
b111100 ,
1#
#130000
0#
b1010101 $
b1010101 (
b110 %
b110 )
#135000
b10101010 -
1#
#140000
0#
#145000
b10101010 !
b10101010 ,
1#
#150000
0#
b1100100 '
b1100100 *
b110010 $
b110010 (
b111 %
b111 )
#155000
b1 -
1#
#160000
0#
#165000
b1 !
b1 ,
1#
#170000
0#
b110010 '
b110010 *
b1100100 $
b1100100 (
#175000
b0 -
1#
#180000
0#
#185000
b0 !
b0 ,
1#
#190000
0#
1&
